Metadata-Version: 2.1
Name: mfdfa-toolkit
Version: 0.0.4
Summary: Multi-Fractal Detrended Fluctuation Analysis (MFDFA)
Home-page: https://github.com/mohsenim/Multifractality
Author: Mahdi Mohseni
Author-email: mohsnei.cs@gmail.com
Classifier: Intended Audience :: Developers
Classifier: Intended Audience :: Science/Research
Classifier: License :: OSI Approved :: MIT License
Classifier: Programming Language :: Python
Classifier: Programming Language :: Python :: 3
License-File: LICENSE
